Metadata-Version: 2.1
Name: inrgif
Version: 1.0.2
Summary: A Python package to make gif from images and videos
Home-page: 
Author: jyotiprakash panigrahi
Author-email: jyotiprakash.work@gmail.com
License: MIT
Platform: UNKNOWN
Classifier: License :: OSI Approved :: MIT License
Classifier: Programming Language :: Python :: 3
Classifier: Programming Language :: Python :: 3.7
Classifier: Programming Language :: Python :: 3.8
Classifier: Programming Language :: Python :: 3.9
License-File: LICENSE
